ezmk/__init__.py
ezmk/constants.py
ezmk/easymark.py
ezmk-1.0.3.dist-info/LICENCE
ezmk-1.0.3.dist-info/METADATA
ezmk-1.0.3.dist-info/WHEEL
ezmk-1.0.3.dist-info/top_level.txt
ezmk-1.0.3.dist-info/RECORD
