Metadata-Version: 2.1
Name: ezmk
Version: 1.0.3
Summary: Easy-to-use color coordination terminal library with simple customization & function binding.
Home-page: https://github.com/ElianGroff/ezmk
Author: Elian Groff
Author-email: elianbgroff@gmail.com
License: MIT
Project-URL: Bug Tracker, https://github.com/ElianGroff/ezmk/issues
Project-URL: Source, https://github.com/ElianGroff/ezmk
Classifier: Programming Language :: Python :: 3
Classifier: Programming Language :: Python
Classifier: Programming Language :: Python :: 3.12
Classifier: Intended Audience :: Developers
Classifier: Topic :: Software Development :: Libraries :: Python Modules
Classifier: Environment :: Console
Classifier: Development Status :: 3 - Alpha
Classifier: Development Status :: 4 - Beta
Classifier: Development Status :: 5 - Production/Stable
Classifier: License :: OSI Approved :: MIT License
License-File: LICENCE
Provides-Extra: test
Requires-Dist: pytest ; extra == 'test'
Requires-Dist: pytest-cov ; extra == 'test'
